[
    {
        "id": "CURRENT_RATIO",
        "color": "hsl(329, 70%, 50%)",
        "data": [
            {
                "x": "2014-02",
                "y": 3.39
            },
            {
                "x": "2014-05",
                "y": 3.34
            },
            {
                "x": "2014-08",
                "y": 4.35
            },
            {
                "x": "2014-11",
                "y": 4.34
            },
            {
                "x": "2015-02",
                "y": 3.72
            },
            {
                "x": "2015-05",
                "y": 4.11
            },
            {
                "x": "2015-08",
                "y": 4.04
            },
            {
                "x": "2015-11",
                "y": 4.26
            },
            {
                "x": "2016-02",
                "y": 4.83
            },
            {
                "x": "2016-05",
                "y": 3.74
            },
            {
                "x": "2016-08",
                "y": 4.92
            },
            {
                "x": "2016-11",
                "y": 3.96
            },
            {
                "x": "2017-02",
                "y": 4.18
            },
            {
                "x": "2017-05",
                "y": 3.08
            },
            {
                "x": "2017-08",
                "y": 3.63
            },
            {
                "x": "2017-11",
                "y": 5.07
            },
            {
                "x": "2018-02",
                "y": 4.33
            },
            {
                "x": "2018-05",
                "y": 3.98
            },
            {
                "x": "2018-08",
                "y": 3.43
            },
            {
                "x": "2018-11",
                "y": 2.8
            },
            {
                "x": "2019-02",
                "y": 2.65
            },
            {
                "x": "2019-05",
                "y": 2.49
            },
            {
                "x": "2019-08",
                "y": 2.25
            },
            {
                "x": "2019-11",
                "y": 2.37
            },
            {
                "x": "2020-02",
                "y": 2.12
            },
            {
                "x": "2020-05",
                "y": 3.03
            },
            {
                "x": "2020-08",
                "y": 2.66
            },
            {
                "x": "2020-11",
                "y": 2.17
            },
            {
                "x": "2021-02",
                "y": 2.16
            },
            {
                "x": "2021-05",
                "y": 2.3
            },
            {
                "x": "2021-08",
                "y": 2.04
            },
            {
                "x": "2021-11",
                "y": 1.65
            },
            {
                "x": "2022-02",
                "y": 1.52
            },
            {
                "x": "2022-05",
                "y": 1.62
            },
            {
                "x": "2022-08",
                "y": 0.6
            },
            {
                "x": "2022-11",
                "y": 0.65
            },
            {
                "x": "2023-02",
                "y": 0.82
            },
            {
                "x": "2023-05",
                "y": 0.91
            },
            {
                "x": "2023-08",
                "y": 0.87
            },
            {
                "x": "2023-11",
                "y": 0.79
            }
        ]
    }
]